MANIFEST.in
README.rst
bootstrap.py
buildout.cfg
setup.py
doc/conf.py
doc/index.rst
xbob/__init__.py
xbob.daq.egg-info/PKG-INFO
xbob.daq.egg-info/SOURCES.txt
xbob.daq.egg-info/dependency_links.txt
xbob.daq.egg-info/entry_points.txt
xbob.daq.egg-info/namespace_packages.txt
xbob.daq.egg-info/not-zip-safe
xbob.daq.egg-info/requires.txt
xbob.daq.egg-info/top_level.txt
xbob/daq/__init__.py
xbob/daq/version.py
xbob/daq/example/__init__.py
xbob/daq/example/capture.py
xbob/daq/ext/BobOutputWriter.cc
xbob/daq/ext/BobOutputWriter.h
xbob/daq/ext/Callbacks.h
xbob/daq/ext/Camera.cc
xbob/daq/ext/Camera.h
xbob/daq/ext/CaptureSystem.cc
xbob/daq/ext/CaptureSystem.h
xbob/daq/ext/ConsoleDisplay.cc
xbob/daq/ext/ConsoleDisplay.h
xbob/daq/ext/Controller.cc
xbob/daq/ext/Controller.h
xbob/daq/ext/Display.cc
xbob/daq/ext/Display.h
xbob/daq/ext/FaceLocalization.cc
xbob/daq/ext/FaceLocalization.h
xbob/daq/ext/NullFaceLocalization.h
xbob/daq/ext/OpenCVFaceLocalization.cc
xbob/daq/ext/OpenCVFaceLocalization.h
xbob/daq/ext/OutputWriter.cc
xbob/daq/ext/OutputWriter.h
xbob/daq/ext/QtDisplay.cc
xbob/daq/ext/QtDisplay.h
xbob/daq/ext/SimpleController.cc
xbob/daq/ext/SimpleController.h
xbob/daq/ext/V4LCamera.cc
xbob/daq/ext/V4LCamera.h
xbob/daq/ext/VideoReaderCamera.cc
xbob/daq/ext/VideoReaderCamera.h
xbob/daq/ext/VisionerFaceLocalization.cc
xbob/daq/ext/VisionerFaceLocalization.h
xbob/daq/ext/all.cc
xbob/daq/ext/main.cc
xbob/daq/ext/version.cc
xbob/daq/test/__init__.py
xbob/daq/test/test_all.py