Metadata-Version: 1.0
Name: xbob.daq
Version: 1.0.5
Summary: Data-Acquisition Extension for Bob-based Applications
Home-page: http://pypi.python.org/pypi/xbob.daq
Author: Andre Anjos
Author-email: andre.anjos@idiap.ch
License: GPLv3
Platform: UNKNOWN
